[{"bgcolor":"419145","cni_personne":"111409891","date_attribution_service":"02\/08\/2017","date_liberation_service":"04\/08\/2017"},{"bgcolor":"358887","cni_personne":"111409891","date_attribution_service":"11\/08\/2017","date_liberation_service":"26\/08\/2017"},{"bgcolor":"693057","cni_personne":"201765779","date_attribution_service":"26\/05\/2017","date_liberation_service":"04\/06\/2017"},{"bgcolor":"441613","cni_personne":"156728295","date_attribution_service":"02\/03\/2017","date_liberation_service":"15\/03\/2017"},{"bgcolor":"620915","cni_personne":"814451245","date_attribution_service":"29\/04\/2017","date_liberation_service":"03\/05\/2017"},{"bgcolor":"692566","cni_personne":"116876436","date_attribution_service":"10\/10\/2017","date_liberation_service":"07\/12\/2017"},{"bgcolor":"238138","cni_personne":"116876436","date_attribution_service":"29\/04\/2017","date_liberation_service":"03\/05\/2017"},{"bgcolor":"252281","cni_personne":"116876436","date_attribution_service":"08\/02\/2018","date_liberation_service":"19\/01\/2018"},{"bgcolor":"994539","cni_personne":"156728295","date_attribution_service":"13\/12\/2017","date_liberation_service":"13\/08\/2017"},{"bgcolor":"656728","cni_personne":"156728295","date_attribution_service":"13\/12\/2017","date_liberation_service":"13\/08\/2017"},{"bgcolor":"442309","cni_personne":"156728295","date_attribution_service":"13\/12\/2017","date_liberation_service":"13\/08\/2017"},{"bgcolor":"388068","cni_personne":"156728295","date_attribution_service":"13\/12\/2017","date_liberation_service":"13\/08\/2017"},{"bgcolor":"121413","cni_personne":"156728295","date_attribution_service":"13\/12\/2017","date_liberation_service":"28\/12\/2017"},{"bgcolor":"139097","cni_personne":"156728295","date_attribution_service":"03\/10\/2017","date_liberation_service":"27\/10\/2017"},{"bgcolor":"911883","cni_personne":"814451245","date_attribution_service":"17\/03\/2017","date_liberation_service":"21\/03\/2017"}]